mistral/__init__.py
mistral/lib/__init__.py
mistral/lib/array_conversion.py
mistral/lib/collate_fn.py
mistral/lib/einshard.py
mistral/lib/example_data.py
mistral/lib/generate.py
mistral/model/__init__.py
mistral/model/attention.py
mistral/model/decoder.py
mistral/model/decoder_block.py
mistral/model/embedding.py
mistral/model/kvcache.py
mistral/model/mistral_lm.py
mistral/model/mistral_model.py
mistral/model/mlp_layer.py
mistral/model/rms_norm.py
mistral/model/rotary_embedding.py
mistral_jax-0.0.3.dist-info/LICENSE
mistral_jax-0.0.3.dist-info/METADATA
mistral_jax-0.0.3.dist-info/WHEEL
mistral_jax-0.0.3.dist-info/top_level.txt
mistral_jax-0.0.3.dist-info/RECORD
