Metadata-Version: 2.1
Name: mistral-jax
Version: 0.0.3
Summary: JAX implementation of the Mistral model.
Author-email: yixiaoer <miyaku@yixiaoer.sg>
Project-URL: Repository, https://github.com/yixiaoer/mistral-jax
Project-URL: Issues, https://github.com/yixiaoer/mistral-jax/issues
Classifier: Development Status :: 4 - Beta
Classifier: Programming Language :: Python
Classifier: License :: OSI Approved :: MIT License
Requires-Python: >=3.10
License-File: LICENSE
Requires-Dist: mypy
Requires-Dist: jax
Requires-Dist: jaxlib
Requires-Dist: torch
Requires-Dist: transformers
Requires-Dist: einops
